setup.cfg
setup.py
sgmanager/__init__.py
sgmanager/__main__.py
sgmanager/cli.py
sgmanager/decorators.py
sgmanager/exceptions.py
sgmanager.egg-info/PKG-INFO
sgmanager.egg-info/SOURCES.txt
sgmanager.egg-info/dependency_links.txt
sgmanager.egg-info/entry_points.txt
sgmanager.egg-info/pbr.json
sgmanager.egg-info/requires.txt
sgmanager.egg-info/top_level.txt
sgmanager/logger/__init__.py
sgmanager/logger/level_handler.py
sgmanager/securitygroups/__init__.py
sgmanager/securitygroups/sgroup.py
sgmanager/securitygroups/srule.py