Metadata-Version: 1.1
Name: sgmanager
Version: 1.4.4
Summary: Security Groups Management Tool
Home-page: https://github.com/gooddata/sgmanager
Author: Petr Benas
Author-email: petr.benas@gooddata.com
License: BSD
Download-URL: https://github.com/gooddata/sgmanager
Platform: UNKNOWN
Classifier: Development Status :: 5 - Production/Stable
Classifier: Environment :: Console
Classifier: Intended Audience :: Developers
Classifier: Intended Audience :: System Administrators
Classifier: License :: OSI Approved :: BSD License
Classifier: Natural Language :: English
Classifier: Operating System :: POSIX
Classifier: Topic :: System :: Networking :: Firewalls
Classifier: Programming Language :: Python
Classifier: Programming Language :: Python :: Implementation :: CPython
